{
  "id": "D10.04",
  "dominio_id": "D10",
  "nome": "Serving, Monitoramento e Drift",
  "nivel": "Staff",
  "carga_horaria": "26-34h",
  "prerequisitos": [
    "APIs",
    "Estatística",
    "SRE"
  ],
  "objetivos": [
    "Servir modelos com latência, escala e observabilidade",
    "Detectar data drift, concept drift e degradação"
  ],
  "pratica_esperada": [
    "Servir modelo via KServe ou BentoML",
    "Monitorar drift com Evidently"
  ],
  "teoria": [
    "batch-inference",
    "online-inference",
    "kserve",
    "model-server",
    "data-drift",
    "concept-drift",
    "calibration",
    "feedback-loop"
  ],
  "algoritmos_tecnicas": [
    "ks-test",
    "psi",
    "population-stability",
    "embedding-drift",
    "canary-scoring"
  ],
  "arquiteturas": [],
  "estruturas_dados": [],
  "modelos_matematicos": [],
  "protocolos": [],
  "livros": [
    "Chip Huyen, Designing Machine Learning Systems",
    "Sculley et al., Hidden Technical Debt in ML Systems"
  ],
  "papers_fundamentais": [
    "Gama et al., A survey on concept drift adaptation, 2014"
  ],
  "ferramentas": [
    "KServe",
    "BentoML",
    "Seldon",
    "Evidently",
    "WhyLabs"
  ],
  "perguntas_entrevista_staff": [
    "Data drift sempre exige retreino?",
    "Como monitorar modelo sem label imediato?"
  ],
  "projetos_reais": [
    "Serviço de inferência com monitoramento de drift e latência"
  ],
  "exercicios": [
    "Calcular PSI",
    "Simular degradação sem label"
  ],
  "tags": [
    "KServe",
    "Drift",
    "Inference",
    "Evidently",
    "Monitoring"
  ]
}